asm_opcode_analyzer/__init__.py
asm_opcode_analyzer/parser.py
asm_opcode_analyzer-1.1.0.dist-info/LICENSE
asm_opcode_analyzer-1.1.0.dist-info/METADATA
asm_opcode_analyzer-1.1.0.dist-info/WHEEL
asm_opcode_analyzer-1.1.0.dist-info/top_level.txt
asm_opcode_analyzer-1.1.0.dist-info/RECORD
